<?xml version="1.0" encoding="utf-8" ?>
<dwsync>
<file name="gl.js" server="216.17.51.112//var/www/html/dpluswhi/" local="131473713140000000" remote="131473713140000000" Dst="2" />
<file name="lt.js" server="216.17.51.112//var/www/html/dpluswhi/" local="131473713150000000" remote="131473713150000000" Dst="2" />
<file name="ja.js" server="216.17.51.112//var/www/html/dpluswhi/" local="131473713150000000" remote="131473713150000000" Dst="2" />
<file name="_translationstatus.txt" server="216.17.51.112//var/www/html/dpluswhi/" local="131473713190000000" remote="131473713190000000" Dst="2" />
<file name="mk.js" server="216.17.51.112//var/www/html/dpluswhi/" local="131473713160000000" remote="131473713160000000" Dst="2" />
<file name="es.js" server="216.17.51.112//var/www/html/dpluswhi/" local="131473713130000000" remote="131473713130000000" Dst="2" />
<file name="ro.js" server="216.17.51.112//var/www/html/dpluswhi/" local="131473713170000000" remote="131473713170000000" Dst="2" />
<file name="he.js" server="216.17.51.112//var/www/html/dpluswhi/" local="131473713140000000" remote="131473713140000000" Dst="2" />
<file name="fr-ca.js" server="216.17.51.112//var/www/html/dpluswhi/" local="131473713140000000" remote="131473713140000000" Dst="2" />
<file name="hi.js" server="216.17.51.112//var/www/html/dpluswhi/" local="131473713140000000" remote="131473713140000000" Dst="2" />
<file name="sv.js" server="216.17.51.112//var/www/html/dpluswhi/" local="131473713170000000" remote="131473713170000000" Dst="2" />
<file name="eo.js" server="216.17.51.112//var/www/html/dpluswhi/" local="131473713130000000" remote="131473713130000000" Dst="2" />
<file name="tr.js" server="216.17.51.112//var/www/html/dpluswhi/" local="131473713180000000" remote="131473713180000000" Dst="2" />
<file name="no.js" server="216.17.51.112//var/www/html/dpluswhi/" local="131473713160000000" remote="131473713160000000" Dst="2" />
<file name="fi.js" server="216.17.51.112//var/www/html/dpluswhi/" local="131473713140000000" remote="131473713140000000" Dst="2" />
<file name="nb.js" server="216.17.51.112//var/www/html/dpluswhi/" local="131473713160000000" remote="131473713160000000" Dst="2" />
<file name="ku.js" server="216.17.51.112//var/www/html/dpluswhi/" local="131473713150000000" remote="131473713150000000" Dst="2" />
<file name="th.js" server="216.17.51.112//var/www/html/dpluswhi/" local="131473713180000000" remote="131473713180000000" Dst="2" />
<file name="el.js" server="216.17.51.112//var/www/html/dpluswhi/" local="131473713130000000" remote="131473713130000000" Dst="2" />
<file name="ru.js" server="216.17.51.112//var/www/html/dpluswhi/" local="131473713170000000" remote="131473713170000000" Dst="2" />
<file name="da.js" server="216.17.51.112//var/www/html/dpluswhi/" local="131473713120000000" remote="131473713120000000" Dst="2" />
<file name="cy.js" server="216.17.51.112//var/www/html/dpluswhi/" local="131473713120000000" remote="131473713120000000" Dst="2" />
<file name="bg.js" server="216.17.51.112//var/www/html/dpluswhi/" local="131473713120000000" remote="131473713120000000" Dst="2" />
<file name="nl.js" server="216.17.51.112//var/www/html/dpluswhi/" local="131473713160000000" remote="131473713160000000" Dst="2" />
<file name="fr.js" server="216.17.51.112//var/www/html/dpluswhi/" local="131473713140000000" remote="131473713140000000" Dst="2" />
<file name="sr-latn.js" server="216.17.51.112//var/www/html/dpluswhi/" local="131473713170000000" remote="131473713170000000" Dst="2" />
<file name="mn.js" server="216.17.51.112//var/www/html/dpluswhi/" local="131473713160000000" remote="131473713160000000" Dst="2" />
<file name="fa.js" server="216.17.51.112//var/www/html/dpluswhi/" local="131473713140000000" remote="131473713140000000" Dst="2" />
<file name="de-ch.js" server="216.17.51.112//var/www/html/dpluswhi/" local="131473713120000000" remote="131473713120000000" Dst="2" />
<file name="ko.js" server="216.17.51.112//var/www/html/dpluswhi/" local="131473713150000000" remote="131473713150000000" Dst="2" />
<file name="vi.js" server="216.17.51.112//var/www/html/dpluswhi/" local="131473713180000000" remote="131473713180000000" Dst="2" />
<file name="en-gb.js" server="216.17.51.112//var/www/html/dpluswhi/" local="131473713130000000" remote="131473713130000000" Dst="2" />
<file name="et.js" server="216.17.51.112//var/www/html/dpluswhi/" local="131473713130000000" remote="131473713130000000" Dst="2" />
<file name="hu.js" server="216.17.51.112//var/www/html/dpluswhi/" local="131473713150000000" remote="131473713150000000" Dst="2" />
<file name="af.js" server="216.17.51.112//var/www/html/dpluswhi/" local="131473713120000000" remote="131473713120000000" Dst="2" />
<file name="fo.js" server="216.17.51.112//var/www/html/dpluswhi/" local="131473713140000000" remote="131473713140000000" Dst="2" />
<file name="pl.js" server="216.17.51.112//var/www/html/dpluswhi/" local="131473713160000000" remote="131473713160000000" Dst="2" />
<file name="lv.js" server="216.17.51.112//var/www/html/dpluswhi/" local="131473713160000000" remote="131473713160000000" Dst="2" />
<file name="ug.js" server="216.17.51.112//var/www/html/dpluswhi/" local="131473713180000000" remote="131473713180000000" Dst="2" />
<file name="en.js" server="216.17.51.112//var/www/html/dpluswhi/" local="131473713130000000" remote="131473713130000000" Dst="2" />
<file name="zh-cn.js" server="216.17.51.112//var/www/html/dpluswhi/" local="131473713180000000" remote="131473713180000000" Dst="2" />
<file name="tt.js" server="216.17.51.112//var/www/html/dpluswhi/" local="131473713180000000" remote="131473713180000000" Dst="2" />
<file name="zh.js" server="216.17.51.112//var/www/html/dpluswhi/" local="131473713180000000" remote="131473713180000000" Dst="2" />
<file name="id.js" server="216.17.51.112//var/www/html/dpluswhi/" local="131473713150000000" remote="131473713150000000" Dst="2" />
<file name="ca.js" server="216.17.51.112//var/www/html/dpluswhi/" local="131473713120000000" remote="131473713120000000" Dst="2" />
<file name="gu.js" server="216.17.51.112//var/www/html/dpluswhi/" local="131473713140000000" remote="131473713140000000" Dst="2" />
<file name="si.js" server="216.17.51.112//var/www/html/dpluswhi/" local="131473713170000000" remote="131473713170000000" Dst="2" />
<file name="sk.js" server="216.17.51.112//var/www/html/dpluswhi/" local="131473713170000000" remote="131473713170000000" Dst="2" />
<file name="eu.js" server="216.17.51.112//var/www/html/dpluswhi/" local="131473713130000000" remote="131473713130000000" Dst="2" />
<file name="sq.js" server="216.17.51.112//var/www/html/dpluswhi/" local="131473713170000000" remote="131473713170000000" Dst="2" />
<file name="cs.js" server="216.17.51.112//var/www/html/dpluswhi/" local="131473713120000000" remote="131473713120000000" Dst="2" />
<file name="ar.js" server="216.17.51.112//var/www/html/dpluswhi/" local="131473713120000000" remote="131473713120000000" Dst="2" />
<file name="uk.js" server="216.17.51.112//var/www/html/dpluswhi/" local="131473713180000000" remote="131473713180000000" Dst="2" />
<file name="km.js" server="216.17.51.112//var/www/html/dpluswhi/" local="131473713150000000" remote="131473713150000000" Dst="2" />
<file name="pt.js" server="216.17.51.112//var/www/html/dpluswhi/" local="131473713160000000" remote="131473713160000000" Dst="2" />
<file name="pt-br.js" server="216.17.51.112//var/www/html/dpluswhi/" local="131473713160000000" remote="131473713160000000" Dst="2" />
<file name="sr.js" server="216.17.51.112//var/www/html/dpluswhi/" local="131473713170000000" remote="131473713170000000" Dst="2" />
<file name="sl.js" server="216.17.51.112//var/www/html/dpluswhi/" local="131473713170000000" remote="131473713170000000" Dst="2" />
<file name="it.js" server="216.17.51.112//var/www/html/dpluswhi/" local="131473713150000000" remote="131473713150000000" Dst="2" />
<file name="de.js" server="216.17.51.112//var/www/html/dpluswhi/" local="131473713130000000" remote="131473713130000000" Dst="2" />
<file name="hr.js" server="216.17.51.112//var/www/html/dpluswhi/" local="131473713150000000" remote="131473713150000000" Dst="2" />
</dwsync>